aioredis_ratelimit/__init__.py
aioredis_ratelimit/decorator.py
aioredis_ratelimit/exceptions.py
aioredis_ratelimit/redis.py
aioredis_ratelimit-0.1.3.dist-info/LICENSE
aioredis_ratelimit-0.1.3.dist-info/METADATA
aioredis_ratelimit-0.1.3.dist-info/WHEEL
aioredis_ratelimit-0.1.3.dist-info/top_level.txt
aioredis_ratelimit-0.1.3.dist-info/RECORD
