Metadata-Version: 2.1
Name: aioredis-ratelimit
Version: 0.1.3
Summary: An asyncio coroutine decorator for limiting calls' rate based on Redis backend and aioredis library.
Home-page: https://github.com/ktolstikhin/aioredis-ratelimit.git
Author: Konstantin Tolstikhin
Author-email: k.tolstikhin@gmail.com
License: MIT
Keywords: decorator,ratelimit,aioredis,redis
Classifier: License :: OSI Approved :: MIT License
Classifier: Programming Language :: Python :: 3.6
Requires-Python: >=3.6
License-File: LICENSE
Requires-Dist: aioredis (<3,>=2)
